initer/__init__.py
initer-0.2.6.dist-info/METADATA
initer-0.2.6.dist-info/WHEEL
initer-0.2.6.dist-info/top_level.txt
initer-0.2.6.dist-info/RECORD
