Metadata-Version: 2.4
Name: initer
Version: 0.2.6
Summary: A Python lib you can use to initialize your Python scripts (Console based / Windowed)
Author: Lilou Palagier
Dynamic: author
Dynamic: summary
